jack_alsa_ctl/__init__.py
jack_alsa_ctl/_version.py
jack_alsa_ctl/cli.py
jack_alsa_ctl/lib.py
jack_alsa_ctl/completion/_jack-alsa-ctl
jack_alsa_ctl-2.0.2.data/scripts/jack-alsa-ctl
jack_alsa_ctl-2.0.2.dist-info/LICENSE
jack_alsa_ctl-2.0.2.dist-info/METADATA
jack_alsa_ctl-2.0.2.dist-info/WHEEL
jack_alsa_ctl-2.0.2.dist-info/top_level.txt
jack_alsa_ctl-2.0.2.dist-info/RECORD
