Metadata-Version: 2.1
Name: jack-alsa-ctl
Version: 2.0.2
Summary: Control JACK audio with ALSA driver easily
Home-page: https://github.com/DCsunset/jack-alsa-ctl
Author: DCsunset
Author-email: DCsunset@protonmail.com
License: AGPL-3.0
Classifier: Environment :: Console
Classifier: Topic :: Multimedia :: Sound/Audio
Classifier: Intended Audience :: End Users/Desktop
Classifier: Programming Language :: Python
Classifier: License :: OSI Approved :: GNU Affero General Public License v3
License-File: LICENSE
